{
	"column_ids": [
		{
			"character_maximum_length": 8000,
			"column_comment": "",
			"column_id": "datavault.s_component_s_dbt_stage_r_component_metric_u_dbt_stage_h.updated",
			"column_is_used": true,
			"column_name": "updated",
			"column_name_detail": "",
			"column_nq_id": "updated",
			"column_order": 1,
			"column_type": "attribute",
			"complete_data_type": "varchar(8000)",
			"conversion_type": null,
			"data_type": "varchar",
			"datetime_precision": null,
			"numeric_precision": 0,
			"numeric_scale": 0
		},
		{
			"character_maximum_length": 8000,
			"column_comment": "",
			"column_id": "datavault.s_component_s_dbt_stage_r_component_metric_u_dbt_stage_h.ldts",
			"column_is_used": true,
			"column_name": "ldts",
			"column_name_detail": "",
			"column_nq_id": "ldts",
			"column_order": 2,
			"column_type": "attribute",
			"complete_data_type": "varchar(8000)",
			"conversion_type": null,
			"data_type": "varchar",
			"datetime_precision": null,
			"numeric_precision": 0,
			"numeric_scale": 0
		},
		{
			"character_maximum_length": 8000,
			"column_comment": "",
			"column_id": "datavault.s_component_s_dbt_stage_r_component_metric_u_dbt_stage_h.component_name",
			"column_is_used": true,
			"column_name": "component_name",
			"column_name_detail": "",
			"column_nq_id": "component_name",
			"column_order": 3,
			"column_type": "attribute",
			"complete_data_type": "varchar(8000)",
			"conversion_type": null,
			"data_type": "varchar",
			"datetime_precision": null,
			"numeric_precision": 0,
			"numeric_scale": 0
		},
		{
			"character_maximum_length": 5,
			"column_comment": "",
			"column_id": "datavault.s_component_s_dbt_stage_r_component_metric_u_dbt_stage_h.ldts_offset_sec",
			"column_is_used": true,
			"column_name": "ldts_offset_sec",
			"column_name_detail": "",
			"column_nq_id": "ldts_offset_sec",
			"column_order": 4,
			"column_type": "attribute",
			"complete_data_type": "decimal(9,9)",
			"conversion_type": null,
			"data_type": "decimal",
			"datetime_precision": null,
			"numeric_precision": 9,
			"numeric_scale": 9
		},
		{
			"character_maximum_length": 8000,
			"column_comment": "",
			"column_id": "datavault.s_component_s_dbt_stage_r_component_metric_u_dbt_stage_h.component_version",
			"column_is_used": true,
			"column_name": "component_version",
			"column_name_detail": "",
			"column_nq_id": "component_version",
			"column_order": 5,
			"column_type": "attribute",
			"complete_data_type": "varchar(8000)",
			"conversion_type": null,
			"data_type": "varchar",
			"datetime_precision": null,
			"numeric_precision": 0,
			"numeric_scale": 0
		},
		{
			"character_maximum_length": 8000,
			"column_comment": "",
			"column_id": "datavault.s_component_s_dbt_stage_r_component_metric_u_dbt_stage_h.misraconfigopendeviation",
			"column_is_used": true,
			"column_name": "misraconfigopendeviation",
			"column_name_detail": "",
			"column_nq_id": "misraconfigopendeviation",
			"column_order": 6,
			"column_type": "attribute",
			"complete_data_type": "varchar(8000)",
			"conversion_type": null,
			"data_type": "varchar",
			"datetime_precision": null,
			"numeric_precision": 0,
			"numeric_scale": 0
		},
		{
			"character_maximum_length": 8000,
			"column_comment": "",
			"column_id": "datavault.s_component_s_dbt_stage_r_component_metric_u_dbt_stage_h.maxdeccov",
			"column_is_used": true,
			"column_name": "maxdeccov",
			"column_name_detail": "",
			"column_nq_id": "maxdeccov",
			"column_order": 7,
			"column_type": "attribute",
			"complete_data_type": "varchar(8000)",
			"conversion_type": null,
			"data_type": "varchar",
			"datetime_precision": null,
			"numeric_precision": 0,
			"numeric_scale": 0
		},
		{
			"character_maximum_length": 8000,
			"column_comment": "",
			"column_id": "datavault.s_component_s_dbt_stage_r_component_metric_u_dbt_stage_h.nrofspecitems_relevant_fulfilledwithdeviations",
			"column_is_used": true,
			"column_name": "nrofspecitems_relevant_fulfilledwithdeviations",
			"column_name_detail": "",
			"column_nq_id": "nrofspecitems_relevant_fulfilledwithdeviations",
			"column_order": 8,
			"column_type": "attribute",
			"complete_data_type": "varchar(8000)",
			"conversion_type": null,
			"data_type": "varchar",
			"datetime_precision": null,
			"numeric_precision": 0,
			"numeric_scale": 0
		},
		{
			"character_maximum_length": 8000,
			"column_comment": "",
			"column_id": "datavault.s_component_s_dbt_stage_r_component_metric_u_dbt_stage_h.designfunctions",
			"column_is_used": true,
			"column_name": "designfunctions",
			"column_name_detail": "",
			"column_nq_id": "designfunctions",
			"column_order": 9,
			"column_type": "attribute",
			"complete_data_type": "varchar(8000)",
			"conversion_type": null,
			"data_type": "varchar",
			"datetime_precision": null,
			"numeric_precision": 0,
			"numeric_scale": 0
		},
		{
			"character_maximum_length": 8000,
			"column_comment": "",
			"column_id": "datavault.s_component_s_dbt_stage_r_component_metric_u_dbt_stage_h.nrofspecitems_notrelevant",
			"column_is_used": true,
			"column_name": "nrofspecitems_notrelevant",
			"column_name_detail": "",
			"column_nq_id": "nrofspecitems_notrelevant",
			"column_order": 10,
			"column_type": "attribute",
			"complete_data_type": "varchar(8000)",
			"conversion_type": null,
			"data_type": "varchar",
			"datetime_precision": null,
			"numeric_precision": 0,
			"numeric_scale": 0
		},
		{
			"character_maximum_length": 8000,
			"column_comment": "",
			"column_id": "datavault.s_component_s_dbt_stage_r_component_metric_u_dbt_stage_h.nrofspecitems_relevantns_fulfilled",
			"column_is_used": true,
			"column_name": "nrofspecitems_relevantns_fulfilled",
			"column_name_detail": "",
			"column_nq_id": "nrofspecitems_relevantns_fulfilled",
			"column_order": 11,
			"column_type": "attribute",
			"complete_data_type": "varchar(8000)",
			"conversion_type": null,
			"data_type": "varchar",
			"datetime_precision": null,
			"numeric_precision": 0,
			"numeric_scale": 0
		},
		{
			"character_maximum_length": 8000,
			"column_comment": "",
			"column_id": "datavault.s_component_s_dbt_stage_r_component_metric_u_dbt_stage_h.minpar",
			"column_is_used": true,
			"column_name": "minpar",
			"column_name_detail": "",
			"column_nq_id": "minpar",
			"column_order": 12,
			"column_type": "attribute",
			"complete_data_type": "varchar(8000)",
			"conversion_type": null,
			"data_type": "varchar",
			"datetime_precision": null,
			"numeric_precision": 0,
			"numeric_scale": 0
		},
		{
			"character_maximum_length": 8000,
			"column_comment": "",
			"column_id": "datavault.s_component_s_dbt_stage_r_component_metric_u_dbt_stage_h.status_testreport_plan",
			"column_is_used": true,
			"column_name": "status_testreport_plan",
			"column_name_detail": "",
			"column_nq_id": "status_testreport_plan",
			"column_order": 13,
			"column_type": "attribute",
			"complete_data_type": "varchar(8000)",
			"conversion_type": null,
			"data_type": "varchar",
			"datetime_precision": null,
			"numeric_precision": 0,
			"numeric_scale": 0
		},
		{
			"character_maximum_length": 8000,
			"column_comment": "",
			"column_id": "datavault.s_component_s_dbt_stage_r_component_metric_u_dbt_stage_h.configurationdecisioncoverage_measured",
			"column_is_used": true,
			"column_name": "configurationdecisioncoverage_measured",
			"column_name_detail": "",
			"column_nq_id": "configurationdecisioncoverage_measured",
			"column_order": 14,
			"column_type": "attribute",
			"complete_data_type": "varchar(8000)",
			"conversion_type": null,
			"data_type": "varchar",
			"datetime_precision": null,
			"numeric_precision": 0,
			"numeric_scale": 0
		},
		{
			"character_maximum_length": 8000,
			"column_comment": "",
			"column_id": "datavault.s_component_s_dbt_stage_r_component_metric_u_dbt_stage_h.tcasesnotok",
			"column_is_used": true,
			"column_name": "tcasesnotok",
			"column_name_detail": "",
			"column_nq_id": "tcasesnotok",
			"column_order": 15,
			"column_type": "attribute",
			"complete_data_type": "varchar(8000)",
			"conversion_type": null,
			"data_type": "varchar",
			"datetime_precision": null,
			"numeric_precision": 0,
			"numeric_scale": 0
		},
		{
			"character_maximum_length": 8000,
			"column_comment": "",
			"column_id": "datavault.s_component_s_dbt_stage_r_component_metric_u_dbt_stage_h.creqswithsafetylevel",
			"column_is_used": true,
			"column_name": "creqswithsafetylevel",
			"column_name_detail": "",
			"column_nq_id": "creqswithsafetylevel",
			"column_order": 16,
			"column_type": "attribute",
			"complete_data_type": "varchar(8000)",
			"conversion_type": null,
			"data_type": "varchar",
			"datetime_precision": null,
			"numeric_precision": 0,
			"numeric_scale": 0
		},
		{
			"character_maximum_length": 8000,
			"column_comment": "",
			"column_id": "datavault.s_component_s_dbt_stage_r_component_metric_u_dbt_stage_h.status_codemetrics",
			"column_is_used": true,
			"column_name": "status_codemetrics",
			"column_name_detail": "",
			"column_nq_id": "status_codemetrics",
			"column_order": 17,
			"column_type": "attribute",
			"complete_data_type": "varchar(8000)",
			"conversion_type": null,
			"data_type": "varchar",
			"datetime_precision": null,
			"numeric_precision": 0,
			"numeric_scale": 0
		},
		{
			"character_maximum_length": 8000,
			"column_comment": "",
			"column_id": "datavault.s_component_s_dbt_stage_r_component_metric_u_dbt_stage_h.tcasesfromvtrnotintestspec",
			"column_is_used": true,
			"column_name": "tcasesfromvtrnotintestspec",
			"column_name_detail": "",
			"column_nq_id": "tcasesfromvtrnotintestspec",
			"column_order": 18,
			"column_type": "attribute",
			"complete_data_type": "varchar(8000)",
			"conversion_type": null,
			"data_type": "varchar",
			"datetime_precision": null,
			"numeric_precision": 0,
			"numeric_scale": 0
		},
		{
			"character_maximum_length": 8000,
			"column_comment": "",
			"column_id": "datavault.s_component_s_dbt_stage_r_component_metric_u_dbt_stage_h.nrofspecitems_relevant_fulfilled",
			"column_is_used": true,
			"column_name": "nrofspecitems_relevant_fulfilled",
			"column_name_detail": "",
			"column_nq_id": "nrofspecitems_relevant_fulfilled",
			"column_order": 19,
			"column_type": "attribute",
			"complete_data_type": "varchar(8000)",
			"conversion_type": null,
			"data_type": "varchar",
			"datetime_precision": null,
			"numeric_precision": 0,
			"numeric_scale": 0
		},
		{
			"character_maximum_length": 8000,
			"column_comment": "",
			"column_id": "datavault.s_component_s_dbt_stage_r_component_metric_u_dbt_stage_h.nrofspecitems_relevantns_fulfilledwithdeviations",
			"column_is_used": true,
			"column_name": "nrofspecitems_relevantns_fulfilledwithdeviations",
			"column_name_detail": "",
			"column_nq_id": "nrofspecitems_relevantns_fulfilledwithdeviations",
			"column_order": 20,
			"column_type": "attribute",
			"complete_data_type": "varchar(8000)",
			"conversion_type": null,
			"data_type": "varchar",
			"datetime_precision": null,
			"numeric_precision": 0,
			"numeric_scale": 0
		},
		{
			"character_maximum_length": 8000,
			"column_comment": "",
			"column_id": "datavault.s_component_s_dbt_stage_r_component_metric_u_dbt_stage_h.status_testreport_plancoverage",
			"column_is_used": true,
			"column_name": "status_testreport_plancoverage",
			"column_name_detail": "",
			"column_nq_id": "status_testreport_plancoverage",
			"column_order": 21,
			"column_type": "attribute",
			"complete_data_type": "varchar(8000)",
			"conversion_type": null,
			"data_type": "varchar",
			"datetime_precision": null,
			"numeric_precision": 0,
			"numeric_scale": 0
		},
		{
			"character_maximum_length": 8000,
			"column_comment": "",
			"column_id": "datavault.s_component_s_dbt_stage_r_component_metric_u_dbt_stage_h.designsubmodules",
			"column_is_used": true,
			"column_name": "designsubmodules",
			"column_name_detail": "",
			"column_nq_id": "designsubmodules",
			"column_order": 22,
			"column_type": "attribute",
			"complete_data_type": "varchar(8000)",
			"conversion_type": null,
			"data_type": "varchar",
			"datetime_precision": null,
			"numeric_precision": 0,
			"numeric_scale": 0
		},
		{
			"character_maximum_length": 8000,
			"column_comment": "",
			"column_id": "datavault.s_component_s_dbt_stage_r_component_metric_u_dbt_stage_h.nrofspecitems",
			"column_is_used": true,
			"column_name": "nrofspecitems",
			"column_name_detail": "",
			"column_nq_id": "nrofspecitems",
			"column_order": 23,
			"column_type": "attribute",
			"complete_data_type": "varchar(8000)",
			"conversion_type": null,
			"data_type": "varchar",
			"datetime_precision": null,
			"numeric_precision": 0,
			"numeric_scale": 0
		},
		{
			"character_maximum_length": 8000,
			"column_comment": "",
			"column_id": "datavault.s_component_s_dbt_stage_r_component_metric_u_dbt_stage_h.nrofspecitems_notrelevant_fulfilledns",
			"column_is_used": true,
			"column_name": "nrofspecitems_notrelevant_fulfilledns",
			"column_name_detail": "",
			"column_nq_id": "nrofspecitems_notrelevant_fulfilledns",
			"column_order": 24,
			"column_type": "attribute",
			"complete_data_type": "varchar(8000)",
			"conversion_type": null,
			"data_type": "varchar",
			"datetime_precision": null,
			"numeric_precision": 0,
			"numeric_scale": 0
		},
		{
			"character_maximum_length": 8000,
			"column_comment": "",
			"column_id": "datavault.s_component_s_dbt_stage_r_component_metric_u_dbt_stage_h.implcal",
			"column_is_used": true,
			"column_name": "implcal",
			"column_name_detail": "",
			"column_nq_id": "implcal",
			"column_order": 25,
			"column_type": "attribute",
			"complete_data_type": "varchar(8000)",
			"conversion_type": null,
			"data_type": "varchar",
			"datetime_precision": null,
			"numeric_precision": 0,
			"numeric_scale": 0
		},
		{
			"character_maximum_length": 8000,
			"column_comment": "",
			"column_id": "datavault.s_component_s_dbt_stage_r_component_metric_u_dbt_stage_h.configurationdecisioncoverage",
			"column_is_used": true,
			"column_name": "configurationdecisioncoverage",
			"column_name_detail": "",
			"column_nq_id": "configurationdecisioncoverage",
			"column_order": 26,
			"column_type": "attribute",
			"complete_data_type": "varchar(8000)",
			"conversion_type": null,
			"data_type": "varchar",
			"datetime_precision": null,
			"numeric_precision": 0,
			"numeric_scale": 0
		},
		{
			"character_maximum_length": 8000,
			"column_comment": "",
			"column_id": "datavault.s_component_s_dbt_stage_r_component_metric_u_dbt_stage_h.nrofrelevantspecitemswithmissingfulfillment",
			"column_is_used": true,
			"column_name": "nrofrelevantspecitemswithmissingfulfillment",
			"column_name_detail": "",
			"column_nq_id": "nrofrelevantspecitemswithmissingfulfillment",
			"column_order": 27,
			"column_type": "attribute",
			"complete_data_type": "varchar(8000)",
			"conversion_type": null,
			"data_type": "varchar",
			"datetime_precision": null,
			"numeric_precision": 0,
			"numeric_scale": 0
		},
		{
			"character_maximum_length": 8000,
			"column_comment": "",
			"column_id": "datavault.s_component_s_dbt_stage_r_component_metric_u_dbt_stage_h.configurationfunctioncoverage_measured",
			"column_is_used": true,
			"column_name": "configurationfunctioncoverage_measured",
			"column_name_detail": "",
			"column_nq_id": "configurationfunctioncoverage_measured",
			"column_order": 28,
			"column_type": "attribute",
			"complete_data_type": "varchar(8000)",
			"conversion_type": null,
			"data_type": "varchar",
			"datetime_precision": null,
			"numeric_precision": 0,
			"numeric_scale": 0
		},
		{
			"character_maximum_length": 8000,
			"column_comment": "",
			"column_id": "datavault.s_component_s_dbt_stage_r_component_metric_u_dbt_stage_h.ppcoverage",
			"column_is_used": true,
			"column_name": "ppcoverage",
			"column_name_detail": "",
			"column_nq_id": "ppcoverage",
			"column_order": 29,
			"column_type": "attribute",
			"complete_data_type": "varchar(8000)",
			"conversion_type": null,
			"data_type": "varchar",
			"datetime_precision": null,
			"numeric_precision": 0,
			"numeric_scale": 0
		},
		{
			"character_maximum_length": 8000,
			"column_comment": "",
			"column_id": "datavault.s_component_s_dbt_stage_r_component_metric_u_dbt_stage_h.overallfunctioncoverage",
			"column_is_used": true,
			"column_name": "overallfunctioncoverage",
			"column_name_detail": "",
			"column_nq_id": "overallfunctioncoverage",
			"column_order": 30,
			"column_type": "attribute",
			"complete_data_type": "varchar(8000)",
			"conversion_type": null,
			"data_type": "varchar",
			"datetime_precision": null,
			"numeric_precision": 0,
			"numeric_scale": 0
		},
		{
			"character_maximum_length": 8000,
			"column_comment": "",
			"column_id": "datavault.s_component_s_dbt_stage_r_component_metric_u_dbt_stage_h.maxfctcov",
			"column_is_used": true,
			"column_name": "maxfctcov",
			"column_name_detail": "",
			"column_nq_id": "maxfctcov",
			"column_order": 31,
			"column_type": "attribute",
			"complete_data_type": "varchar(8000)",
			"conversion_type": null,
			"data_type": "varchar",
			"datetime_precision": null,
			"numeric_precision": 0,
			"numeric_scale": 0
		},
		{
			"character_maximum_length": 8000,
			"column_comment": "",
			"column_id": "datavault.s_component_s_dbt_stage_r_component_metric_u_dbt_stage_h.maxpar",
			"column_is_used": true,
			"column_name": "maxpar",
			"column_name_detail": "",
			"column_nq_id": "maxpar",
			"column_order": 32,
			"column_type": "attribute",
			"complete_data_type": "varchar(8000)",
			"conversion_type": null,
			"data_type": "varchar",
			"datetime_precision": null,
			"numeric_precision": 0,
			"numeric_scale": 0
		},
		{
			"character_maximum_length": 8000,
			"column_comment": "",
			"column_id": "datavault.s_component_s_dbt_stage_r_component_metric_u_dbt_stage_h.unjustifiedcodemetricviolations",
			"column_is_used": true,
			"column_name": "unjustifiedcodemetricviolations",
			"column_name_detail": "",
			"column_nq_id": "unjustifiedcodemetricviolations",
			"column_order": 33,
			"column_type": "attribute",
			"complete_data_type": "varchar(8000)",
			"conversion_type": null,
			"data_type": "varchar",
			"datetime_precision": null,
			"numeric_precision": 0,
			"numeric_scale": 0
		},
		{
			"character_maximum_length": 8000,
			"column_comment": "",
			"column_id": "datavault.s_component_s_dbt_stage_r_component_metric_u_dbt_stage_h.nrofirrelevantspecitemswithfulfillment",
			"column_is_used": true,
			"column_name": "nrofirrelevantspecitemswithfulfillment",
			"column_name_detail": "",
			"column_nq_id": "nrofirrelevantspecitemswithfulfillment",
			"column_order": 34,
			"column_type": "attribute",
			"complete_data_type": "varchar(8000)",
			"conversion_type": null,
			"data_type": "varchar",
			"datetime_precision": null,
			"numeric_precision": 0,
			"numeric_scale": 0
		},
		{
			"character_maximum_length": 8000,
			"column_comment": "",
			"column_id": "datavault.s_component_s_dbt_stage_r_component_metric_u_dbt_stage_h.status_testreport",
			"column_is_used": true,
			"column_name": "status_testreport",
			"column_name_detail": "",
			"column_nq_id": "status_testreport",
			"column_order": 35,
			"column_type": "attribute",
			"complete_data_type": "varchar(8000)",
			"conversion_type": null,
			"data_type": "varchar",
			"datetime_precision": null,
			"numeric_precision": 0,
			"numeric_scale": 0
		},
		{
			"character_maximum_length": 8000,
			"column_comment": "",
			"column_id": "datavault.s_component_s_dbt_stage_r_component_metric_u_dbt_stage_h.overallbranchcoverage_measured",
			"column_is_used": true,
			"column_name": "overallbranchcoverage_measured",
			"column_name_detail": "",
			"column_nq_id": "overallbranchcoverage_measured",
			"column_order": 36,
			"column_type": "attribute",
			"complete_data_type": "varchar(8000)",
			"conversion_type": null,
			"data_type": "varchar",
			"datetime_precision": null,
			"numeric_precision": 0,
			"numeric_scale": 0
		},
		{
			"character_maximum_length": 8000,
			"column_comment": "",
			"column_id": "datavault.s_component_s_dbt_stage_r_component_metric_u_dbt_stage_h.nrofspecitems_relevant_fulfilledns",
			"column_is_used": true,
			"column_name": "nrofspecitems_relevant_fulfilledns",
			"column_name_detail": "",
			"column_nq_id": "nrofspecitems_relevant_fulfilledns",
			"column_order": 37,
			"column_type": "attribute",
			"complete_data_type": "varchar(8000)",
			"conversion_type": null,
			"data_type": "varchar",
			"datetime_precision": null,
			"numeric_precision": 0,
			"numeric_scale": 0
		},
		{
			"character_maximum_length": 8000,
			"column_comment": "",
			"column_id": "datavault.s_component_s_dbt_stage_r_component_metric_u_dbt_stage_h.tcasesplanned",
			"column_is_used": true,
			"column_name": "tcasesplanned",
			"column_name_detail": "",
			"column_nq_id": "tcasesplanned",
			"column_order": 38,
			"column_type": "attribute",
			"complete_data_type": "varchar(8000)",
			"conversion_type": null,
			"data_type": "varchar",
			"datetime_precision": null,
			"numeric_precision": 0,
			"numeric_scale": 0
		},
		{
			"character_maximum_length": 8000,
			"column_comment": "",
			"column_id": "datavault.s_component_s_dbt_stage_r_component_metric_u_dbt_stage_h.nrofspecitems_relevantns_fulfilledns",
			"column_is_used": true,
			"column_name": "nrofspecitems_relevantns_fulfilledns",
			"column_name_detail": "",
			"column_nq_id": "nrofspecitems_relevantns_fulfilledns",
			"column_order": 39,
			"column_type": "attribute",
			"complete_data_type": "varchar(8000)",
			"conversion_type": null,
			"data_type": "varchar",
			"datetime_precision": null,
			"numeric_precision": 0,
			"numeric_scale": 0
		},
		{
			"character_maximum_length": 8000,
			"column_comment": "",
			"column_id": "datavault.s_component_s_dbt_stage_r_component_metric_u_dbt_stage_h.implpth",
			"column_is_used": true,
			"column_name": "implpth",
			"column_name_detail": "",
			"column_nq_id": "implpth",
			"column_order": 40,
			"column_type": "attribute",
			"complete_data_type": "varchar(8000)",
			"conversion_type": null,
			"data_type": "varchar",
			"datetime_precision": null,
			"numeric_precision": 0,
			"numeric_scale": 0
		},
		{
			"character_maximum_length": 8000,
			"column_comment": "",
			"column_id": "datavault.s_component_s_dbt_stage_r_component_metric_u_dbt_stage_h.ppcoverageqm",
			"column_is_used": true,
			"column_name": "ppcoverageqm",
			"column_name_detail": "",
			"column_nq_id": "ppcoverageqm",
			"column_order": 41,
			"column_type": "attribute",
			"complete_data_type": "varchar(8000)",
			"conversion_type": null,
			"data_type": "varchar",
			"datetime_precision": null,
			"numeric_precision": 0,
			"numeric_scale": 0
		},
		{
			"character_maximum_length": 8000,
			"column_comment": "",
			"column_id": "datavault.s_component_s_dbt_stage_r_component_metric_u_dbt_stage_h.nrofspecitems_relevantns_notfulfilled",
			"column_is_used": true,
			"column_name": "nrofspecitems_relevantns_notfulfilled",
			"column_name_detail": "",
			"column_nq_id": "nrofspecitems_relevantns_notfulfilled",
			"column_order": 42,
			"column_type": "attribute",
			"complete_data_type": "varchar(8000)",
			"conversion_type": null,
			"data_type": "varchar",
			"datetime_precision": null,
			"numeric_precision": 0,
			"numeric_scale": 0
		},
		{
			"character_maximum_length": 8000,
			"column_comment": "",
			"column_id": "datavault.s_component_s_dbt_stage_r_component_metric_u_dbt_stage_h.creqswithtracetotcase",
			"column_is_used": true,
			"column_name": "creqswithtracetotcase",
			"column_name_detail": "",
			"column_nq_id": "creqswithtracetotcase",
			"column_order": 43,
			"column_type": "attribute",
			"complete_data_type": "varchar(8000)",
			"conversion_type": null,
			"data_type": "varchar",
			"datetime_precision": null,
			"numeric_precision": 0,
			"numeric_scale": 0
		},
		{
			"character_maximum_length": 8000,
			"column_comment": "",
			"column_id": "datavault.s_component_s_dbt_stage_r_component_metric_u_dbt_stage_h.desccontainer",
			"column_is_used": true,
			"column_name": "desccontainer",
			"column_name_detail": "",
			"column_nq_id": "desccontainer",
			"column_order": 44,
			"column_type": "attribute",
			"complete_data_type": "varchar(8000)",
			"conversion_type": null,
			"data_type": "varchar",
			"datetime_precision": null,
			"numeric_precision": 0,
			"numeric_scale": 0
		},
		{
			"character_maximum_length": 8000,
			"column_comment": "",
			"column_id": "datavault.s_component_s_dbt_stage_r_component_metric_u_dbt_stage_h.nrofspecitems_notrelevant_fulfilledwithdeviations",
			"column_is_used": true,
			"column_name": "nrofspecitems_notrelevant_fulfilledwithdeviations",
			"column_name_detail": "",
			"column_nq_id": "nrofspecitems_notrelevant_fulfilledwithdeviations",
			"column_order": 45,
			"column_type": "attribute",
			"complete_data_type": "varchar(8000)",
			"conversion_type": null,
			"data_type": "varchar",
			"datetime_precision": null,
			"numeric_precision": 0,
			"numeric_scale": 0
		},
		{
			"character_maximum_length": 8000,
			"column_comment": "",
			"column_id": "datavault.s_component_s_dbt_stage_r_component_metric_u_dbt_stage_h.implpar",
			"column_is_used": true,
			"column_name": "implpar",
			"column_name_detail": "",
			"column_nq_id": "implpar",
			"column_order": 46,
			"column_type": "attribute",
			"complete_data_type": "varchar(8000)",
			"conversion_type": null,
			"data_type": "varchar",
			"datetime_precision": null,
			"numeric_precision": 0,
			"numeric_scale": 0
		},
		{
			"character_maximum_length": 8000,
			"column_comment": "",
			"column_id": "datavault.s_component_s_dbt_stage_r_component_metric_u_dbt_stage_h.maxpth",
			"column_is_used": true,
			"column_name": "maxpth",
			"column_name_detail": "",
			"column_nq_id": "maxpth",
			"column_order": 47,
			"column_type": "attribute",
			"complete_data_type": "varchar(8000)",
			"conversion_type": null,
			"data_type": "varchar",
			"datetime_precision": null,
			"numeric_precision": 0,
			"numeric_scale": 0
		},
		{
			"character_maximum_length": 8000,
			"column_comment": "",
			"column_id": "datavault.s_component_s_dbt_stage_r_component_metric_u_dbt_stage_h.tcasesexecutioncoverage",
			"column_is_used": true,
			"column_name": "tcasesexecutioncoverage",
			"column_name_detail": "",
			"column_nq_id": "tcasesexecutioncoverage",
			"column_order": 48,
			"column_type": "attribute",
			"complete_data_type": "varchar(8000)",
			"conversion_type": null,
			"data_type": "varchar",
			"datetime_precision": null,
			"numeric_precision": 0,
			"numeric_scale": 0
		},
		{
			"character_maximum_length": 8000,
			"column_comment": "",
			"column_id": "datavault.s_component_s_dbt_stage_r_component_metric_u_dbt_stage_h.overallfunctioncoverage_measured",
			"column_is_used": true,
			"column_name": "overallfunctioncoverage_measured",
			"column_name_detail": "",
			"column_nq_id": "overallfunctioncoverage_measured",
			"column_order": 49,
			"column_type": "attribute",
			"complete_data_type": "varchar(8000)",
			"conversion_type": null,
			"data_type": "varchar",
			"datetime_precision": null,
			"numeric_precision": 0,
			"numeric_scale": 0
		},
		{
			"character_maximum_length": 8000,
			"column_comment": "",
			"column_id": "datavault.s_component_s_dbt_stage_r_component_metric_u_dbt_stage_h.descparameter",
			"column_is_used": true,
			"column_name": "descparameter",
			"column_name_detail": "",
			"column_nq_id": "descparameter",
			"column_order": 50,
			"column_type": "attribute",
			"complete_data_type": "varchar(8000)",
			"conversion_type": null,
			"data_type": "varchar",
			"datetime_precision": null,
			"numeric_precision": 0,
			"numeric_scale": 0
		},
		{
			"character_maximum_length": 8000,
			"column_comment": "",
			"column_id": "datavault.s_component_s_dbt_stage_r_component_metric_u_dbt_stage_h.status_misra",
			"column_is_used": true,
			"column_name": "status_misra",
			"column_name_detail": "",
			"column_nq_id": "status_misra",
			"column_order": 51,
			"column_type": "attribute",
			"complete_data_type": "varchar(8000)",
			"conversion_type": null,
			"data_type": "varchar",
			"datetime_precision": null,
			"numeric_precision": 0,
			"numeric_scale": 0
		},
		{
			"character_maximum_length": 8000,
			"column_comment": "",
			"column_id": "datavault.s_component_s_dbt_stage_r_component_metric_u_dbt_stage_h.misra_ruleset",
			"column_is_used": true,
			"column_name": "misra_ruleset",
			"column_name_detail": "",
			"column_nq_id": "misra_ruleset",
			"column_order": 52,
			"column_type": "attribute",
			"complete_data_type": "varchar(8000)",
			"conversion_type": null,
			"data_type": "varchar",
			"datetime_precision": null,
			"numeric_precision": 0,
			"numeric_scale": 0
		},
		{
			"character_maximum_length": 8000,
			"column_comment": "",
			"column_id": "datavault.s_component_s_dbt_stage_r_component_metric_u_dbt_stage_h.configurationbranchcoverage",
			"column_is_used": true,
			"column_name": "configurationbranchcoverage",
			"column_name_detail": "",
			"column_nq_id": "configurationbranchcoverage",
			"column_order": 53,
			"column_type": "attribute",
			"complete_data_type": "varchar(8000)",
			"conversion_type": null,
			"data_type": "varchar",
			"datetime_precision": null,
			"numeric_precision": 0,
			"numeric_scale": 0
		},
		{
			"character_maximum_length": 8000,
			"column_comment": "",
			"column_id": "datavault.s_component_s_dbt_stage_r_component_metric_u_dbt_stage_h.minpth",
			"column_is_used": true,
			"column_name": "minpth",
			"column_name_detail": "",
			"column_nq_id": "minpth",
			"column_order": 54,
			"column_type": "attribute",
			"complete_data_type": "varchar(8000)",
			"conversion_type": null,
			"data_type": "varchar",
			"datetime_precision": null,
			"numeric_precision": 0,
			"numeric_scale": 0
		},
		{
			"character_maximum_length": 8000,
			"column_comment": "",
			"column_id": "datavault.s_component_s_dbt_stage_r_component_metric_u_dbt_stage_h.nrofspecitems_relevant",
			"column_is_used": true,
			"column_name": "nrofspecitems_relevant",
			"column_name_detail": "",
			"column_nq_id": "nrofspecitems_relevant",
			"column_order": 55,
			"column_type": "attribute",
			"complete_data_type": "varchar(8000)",
			"conversion_type": null,
			"data_type": "varchar",
			"datetime_precision": null,
			"numeric_precision": 0,
			"numeric_scale": 0
		},
		{
			"character_maximum_length": 8000,
			"column_comment": "",
			"column_id": "datavault.s_component_s_dbt_stage_r_component_metric_u_dbt_stage_h.mincyc",
			"column_is_used": true,
			"column_name": "mincyc",
			"column_name_detail": "",
			"column_nq_id": "mincyc",
			"column_order": 56,
			"column_type": "attribute",
			"complete_data_type": "varchar(8000)",
			"conversion_type": null,
			"data_type": "varchar",
			"datetime_precision": null,
			"numeric_precision": 0,
			"numeric_scale": 0
		},
		{
			"character_maximum_length": 8000,
			"column_comment": "",
			"column_id": "datavault.s_component_s_dbt_stage_r_component_metric_u_dbt_stage_h.misraconfigurations",
			"column_is_used": true,
			"column_name": "misraconfigurations",
			"column_name_detail": "",
			"column_nq_id": "misraconfigurations",
			"column_order": 57,
			"column_type": "attribute",
			"complete_data_type": "varchar(8000)",
			"conversion_type": null,
			"data_type": "varchar",
			"datetime_precision": null,
			"numeric_precision": 0,
			"numeric_scale": 0
		},
		{
			"character_maximum_length": 8000,
			"column_comment": "",
			"column_id": "datavault.s_component_s_dbt_stage_r_component_metric_u_dbt_stage_h.maxcyc",
			"column_is_used": true,
			"column_name": "maxcyc",
			"column_name_detail": "",
			"column_nq_id": "maxcyc",
			"column_order": 58,
			"column_type": "attribute",
			"complete_data_type": "varchar(8000)",
			"conversion_type": null,
			"data_type": "varchar",
			"datetime_precision": null,
			"numeric_precision": 0,
			"numeric_scale": 0
		},
		{
			"character_maximum_length": 8000,
			"column_comment": "",
			"column_id": "datavault.s_component_s_dbt_stage_r_component_metric_u_dbt_stage_h.tcases",
			"column_is_used": true,
			"column_name": "tcases",
			"column_name_detail": "",
			"column_nq_id": "tcases",
			"column_order": 59,
			"column_type": "attribute",
			"complete_data_type": "varchar(8000)",
			"conversion_type": null,
			"data_type": "varchar",
			"datetime_precision": null,
			"numeric_precision": 0,
			"numeric_scale": 0
		},
		{
			"character_maximum_length": 8000,
			"column_comment": "",
			"column_id": "datavault.s_component_s_dbt_stage_r_component_metric_u_dbt_stage_h.tcasespassedorjustified",
			"column_is_used": true,
			"column_name": "tcasespassedorjustified",
			"column_name_detail": "",
			"column_nq_id": "tcasespassedorjustified",
			"column_order": 60,
			"column_type": "attribute",
			"complete_data_type": "varchar(8000)",
			"conversion_type": null,
			"data_type": "varchar",
			"datetime_precision": null,
			"numeric_precision": 0,
			"numeric_scale": 0
		},
		{
			"character_maximum_length": 8000,
			"column_comment": "",
			"column_id": "datavault.s_component_s_dbt_stage_r_component_metric_u_dbt_stage_h.overalldecisioncoverage_measured",
			"column_is_used": true,
			"column_name": "overalldecisioncoverage_measured",
			"column_name_detail": "",
			"column_nq_id": "overalldecisioncoverage_measured",
			"column_order": 61,
			"column_type": "attribute",
			"complete_data_type": "varchar(8000)",
			"conversion_type": null,
			"data_type": "varchar",
			"datetime_precision": null,
			"numeric_precision": 0,
			"numeric_scale": 0
		},
		{
			"character_maximum_length": 8000,
			"column_comment": "",
			"column_id": "datavault.s_component_s_dbt_stage_r_component_metric_u_dbt_stage_h.creqspecchapters",
			"column_is_used": true,
			"column_name": "creqspecchapters",
			"column_name_detail": "",
			"column_nq_id": "creqspecchapters",
			"column_order": 62,
			"column_type": "attribute",
			"complete_data_type": "varchar(8000)",
			"conversion_type": null,
			"data_type": "varchar",
			"datetime_precision": null,
			"numeric_precision": 0,
			"numeric_scale": 0
		},
		{
			"character_maximum_length": 8000,
			"column_comment": "",
			"column_id": "datavault.s_component_s_dbt_stage_r_component_metric_u_dbt_stage_h.tcasesfromtestspec",
			"column_is_used": true,
			"column_name": "tcasesfromtestspec",
			"column_name_detail": "",
			"column_nq_id": "tcasesfromtestspec",
			"column_order": 63,
			"column_type": "attribute",
			"complete_data_type": "varchar(8000)",
			"conversion_type": null,
			"data_type": "varchar",
			"datetime_precision": null,
			"numeric_precision": 0,
			"numeric_scale": 0
		},
		{
			"character_maximum_length": 8000,
			"column_comment": "",
			"column_id": "datavault.s_component_s_dbt_stage_r_component_metric_u_dbt_stage_h.nrofspecitems_notrelevant_fulfilled",
			"column_is_used": true,
			"column_name": "nrofspecitems_notrelevant_fulfilled",
			"column_name_detail": "",
			"column_nq_id": "nrofspecitems_notrelevant_fulfilled",
			"column_order": 64,
			"column_type": "attribute",
			"complete_data_type": "varchar(8000)",
			"conversion_type": null,
			"data_type": "varchar",
			"datetime_precision": null,
			"numeric_precision": 0,
			"numeric_scale": 0
		},
		{
			"character_maximum_length": 8000,
			"column_comment": "",
			"column_id": "datavault.s_component_s_dbt_stage_r_component_metric_u_dbt_stage_h.mincal",
			"column_is_used": true,
			"column_name": "mincal",
			"column_name_detail": "",
			"column_nq_id": "mincal",
			"column_order": 65,
			"column_type": "attribute",
			"complete_data_type": "varchar(8000)",
			"conversion_type": null,
			"data_type": "varchar",
			"datetime_precision": null,
			"numeric_precision": 0,
			"numeric_scale": 0
		},
		{
			"character_maximum_length": 8000,
			"column_comment": "",
			"column_id": "datavault.s_component_s_dbt_stage_r_component_metric_u_dbt_stage_h.designfiles",
			"column_is_used": true,
			"column_name": "designfiles",
			"column_name_detail": "",
			"column_nq_id": "designfiles",
			"column_order": 66,
			"column_type": "attribute",
			"complete_data_type": "varchar(8000)",
			"conversion_type": null,
			"data_type": "varchar",
			"datetime_precision": null,
			"numeric_precision": 0,
			"numeric_scale": 0
		},
		{
			"character_maximum_length": 8000,
			"column_comment": "",
			"column_id": "datavault.s_component_s_dbt_stage_r_component_metric_u_dbt_stage_h.safetymanualchapter",
			"column_is_used": true,
			"column_name": "safetymanualchapter",
			"column_name_detail": "",
			"column_nq_id": "safetymanualchapter",
			"column_order": 67,
			"column_type": "attribute",
			"complete_data_type": "varchar(8000)",
			"conversion_type": null,
			"data_type": "varchar",
			"datetime_precision": null,
			"numeric_precision": 0,
			"numeric_scale": 0
		},
		{
			"character_maximum_length": 8000,
			"column_comment": "",
			"column_id": "datavault.s_component_s_dbt_stage_r_component_metric_u_dbt_stage_h.misrarules",
			"column_is_used": true,
			"column_name": "misrarules",
			"column_name_detail": "",
			"column_nq_id": "misrarules",
			"column_order": 68,
			"column_type": "attribute",
			"complete_data_type": "varchar(8000)",
			"conversion_type": null,
			"data_type": "varchar",
			"datetime_precision": null,
			"numeric_precision": 0,
			"numeric_scale": 0
		},
		{
			"character_maximum_length": 8000,
			"column_comment": "",
			"column_id": "datavault.s_component_s_dbt_stage_r_component_metric_u_dbt_stage_h.tcasesfromtestspecnotinvtr",
			"column_is_used": true,
			"column_name": "tcasesfromtestspecnotinvtr",
			"column_name_detail": "",
			"column_nq_id": "tcasesfromtestspecnotinvtr",
			"column_order": 69,
			"column_type": "attribute",
			"complete_data_type": "varchar(8000)",
			"conversion_type": null,
			"data_type": "varchar",
			"datetime_precision": null,
			"numeric_precision": 0,
			"numeric_scale": 0
		},
		{
			"character_maximum_length": 8000,
			"column_comment": "",
			"column_id": "datavault.s_component_s_dbt_stage_r_component_metric_u_dbt_stage_h.implcyc",
			"column_is_used": true,
			"column_name": "implcyc",
			"column_name_detail": "",
			"column_nq_id": "implcyc",
			"column_order": 70,
			"column_type": "attribute",
			"complete_data_type": "varchar(8000)",
			"conversion_type": null,
			"data_type": "varchar",
			"datetime_precision": null,
			"numeric_precision": 0,
			"numeric_scale": 0
		},
		{
			"character_maximum_length": 8000,
			"column_comment": "",
			"column_id": "datavault.s_component_s_dbt_stage_r_component_metric_u_dbt_stage_h.nrofspecitems_notrelevant_notfulfilled",
			"column_is_used": true,
			"column_name": "nrofspecitems_notrelevant_notfulfilled",
			"column_name_detail": "",
			"column_nq_id": "nrofspecitems_notrelevant_notfulfilled",
			"column_order": 71,
			"column_type": "attribute",
			"complete_data_type": "varchar(8000)",
			"conversion_type": null,
			"data_type": "varchar",
			"datetime_precision": null,
			"numeric_precision": 0,
			"numeric_scale": 0
		},
		{
			"character_maximum_length": 8000,
			"column_comment": "",
			"column_id": "datavault.s_component_s_dbt_stage_r_component_metric_u_dbt_stage_h.nrofspecitemswithmissingrelevance",
			"column_is_used": true,
			"column_name": "nrofspecitemswithmissingrelevance",
			"column_name_detail": "",
			"column_nq_id": "nrofspecitemswithmissingrelevance",
			"column_order": 72,
			"column_type": "attribute",
			"complete_data_type": "varchar(8000)",
			"conversion_type": null,
			"data_type": "varchar",
			"datetime_precision": null,
			"numeric_precision": 0,
			"numeric_scale": 0
		},
		{
			"character_maximum_length": 8000,
			"column_comment": "",
			"column_id": "datavault.s_component_s_dbt_stage_r_component_metric_u_dbt_stage_h.nrofspecitems_relevantns",
			"column_is_used": true,
			"column_name": "nrofspecitems_relevantns",
			"column_name_detail": "",
			"column_nq_id": "nrofspecitems_relevantns",
			"column_order": 73,
			"column_type": "attribute",
			"complete_data_type": "varchar(8000)",
			"conversion_type": null,
			"data_type": "varchar",
			"datetime_precision": null,
			"numeric_precision": 0,
			"numeric_scale": 0
		},
		{
			"character_maximum_length": 8000,
			"column_comment": "",
			"column_id": "datavault.s_component_s_dbt_stage_r_component_metric_u_dbt_stage_h.implmif",
			"column_is_used": true,
			"column_name": "implmif",
			"column_name_detail": "",
			"column_nq_id": "implmif",
			"column_order": 74,
			"column_type": "attribute",
			"complete_data_type": "varchar(8000)",
			"conversion_type": null,
			"data_type": "varchar",
			"datetime_precision": null,
			"numeric_precision": 0,
			"numeric_scale": 0
		},
		{
			"character_maximum_length": 8000,
			"column_comment": "",
			"column_id": "datavault.s_component_s_dbt_stage_r_component_metric_u_dbt_stage_h.nrofspecitemswhicharefulfilledandhavenotrace",
			"column_is_used": true,
			"column_name": "nrofspecitemswhicharefulfilledandhavenotrace",
			"column_name_detail": "",
			"column_nq_id": "nrofspecitemswhicharefulfilledandhavenotrace",
			"column_order": 75,
			"column_type": "attribute",
			"complete_data_type": "varchar(8000)",
			"conversion_type": null,
			"data_type": "varchar",
			"datetime_precision": null,
			"numeric_precision": 0,
			"numeric_scale": 0
		},
		{
			"character_maximum_length": 8000,
			"column_comment": "",
			"column_id": "datavault.s_component_s_dbt_stage_r_component_metric_u_dbt_stage_h.maxcal",
			"column_is_used": true,
			"column_name": "maxcal",
			"column_name_detail": "",
			"column_nq_id": "maxcal",
			"column_order": 76,
			"column_type": "attribute",
			"complete_data_type": "varchar(8000)",
			"conversion_type": null,
			"data_type": "varchar",
			"datetime_precision": null,
			"numeric_precision": 0,
			"numeric_scale": 0
		},
		{
			"character_maximum_length": 8000,
			"column_comment": "",
			"column_id": "datavault.s_component_s_dbt_stage_r_component_metric_u_dbt_stage_h.configurationfunctioncoverage",
			"column_is_used": true,
			"column_name": "configurationfunctioncoverage",
			"column_name_detail": "",
			"column_nq_id": "configurationfunctioncoverage",
			"column_order": 77,
			"column_type": "attribute",
			"complete_data_type": "varchar(8000)",
			"conversion_type": null,
			"data_type": "varchar",
			"datetime_precision": null,
			"numeric_precision": 0,
			"numeric_scale": 0
		},
		{
			"character_maximum_length": 8000,
			"column_comment": "",
			"column_id": "datavault.s_component_s_dbt_stage_r_component_metric_u_dbt_stage_h.misraconfigopennotjustyfied",
			"column_is_used": true,
			"column_name": "misraconfigopennotjustyfied",
			"column_name_detail": "",
			"column_nq_id": "misraconfigopennotjustyfied",
			"column_order": 78,
			"column_type": "attribute",
			"complete_data_type": "varchar(8000)",
			"conversion_type": null,
			"data_type": "varchar",
			"datetime_precision": null,
			"numeric_precision": 0,
			"numeric_scale": 0
		},
		{
			"character_maximum_length": 8000,
			"column_comment": "",
			"column_id": "datavault.s_component_s_dbt_stage_r_component_metric_u_dbt_stage_h.tcaseslinkedwithasilcreq_executioncoverage",
			"column_is_used": true,
			"column_name": "tcaseslinkedwithasilcreq_executioncoverage",
			"column_name_detail": "",
			"column_nq_id": "tcaseslinkedwithasilcreq_executioncoverage",
			"column_order": 79,
			"column_type": "attribute",
			"complete_data_type": "varchar(8000)",
			"conversion_type": null,
			"data_type": "varchar",
			"datetime_precision": null,
			"numeric_precision": 0,
			"numeric_scale": 0
		},
		{
			"character_maximum_length": 8000,
			"column_comment": "",
			"column_id": "datavault.s_component_s_dbt_stage_r_component_metric_u_dbt_stage_h.safetymanualitems",
			"column_is_used": true,
			"column_name": "safetymanualitems",
			"column_name_detail": "",
			"column_nq_id": "safetymanualitems",
			"column_order": 80,
			"column_type": "attribute",
			"complete_data_type": "varchar(8000)",
			"conversion_type": null,
			"data_type": "varchar",
			"datetime_precision": null,
			"numeric_precision": 0,
			"numeric_scale": 0
		},
		{
			"character_maximum_length": 8000,
			"column_comment": "",
			"column_id": "datavault.s_component_s_dbt_stage_r_component_metric_u_dbt_stage_h.overallbranchcoverage",
			"column_is_used": true,
			"column_name": "overallbranchcoverage",
			"column_name_detail": "",
			"column_nq_id": "overallbranchcoverage",
			"column_order": 81,
			"column_type": "attribute",
			"complete_data_type": "varchar(8000)",
			"conversion_type": null,
			"data_type": "varchar",
			"datetime_precision": null,
			"numeric_precision": 0,
			"numeric_scale": 0
		},
		{
			"character_maximum_length": 8000,
			"column_comment": "",
			"column_id": "datavault.s_component_s_dbt_stage_r_component_metric_u_dbt_stage_h.minmif",
			"column_is_used": true,
			"column_name": "minmif",
			"column_name_detail": "",
			"column_nq_id": "minmif",
			"column_order": 82,
			"column_type": "attribute",
			"complete_data_type": "varchar(8000)",
			"conversion_type": null,
			"data_type": "varchar",
			"datetime_precision": null,
			"numeric_precision": 0,
			"numeric_scale": 0
		},
		{
			"character_maximum_length": 8000,
			"column_comment": "",
			"column_id": "datavault.s_component_s_dbt_stage_r_component_metric_u_dbt_stage_h.status_preprocessorcoverage",
			"column_is_used": true,
			"column_name": "status_preprocessorcoverage",
			"column_name_detail": "",
			"column_nq_id": "status_preprocessorcoverage",
			"column_order": 83,
			"column_type": "attribute",
			"complete_data_type": "varchar(8000)",
			"conversion_type": null,
			"data_type": "varchar",
			"datetime_precision": null,
			"numeric_precision": 0,
			"numeric_scale": 0
		},
		{
			"character_maximum_length": 8000,
			"column_comment": "",
			"column_id": "datavault.s_component_s_dbt_stage_r_component_metric_u_dbt_stage_h.designdiagram",
			"column_is_used": true,
			"column_name": "designdiagram",
			"column_name_detail": "",
			"column_nq_id": "designdiagram",
			"column_order": 84,
			"column_type": "attribute",
			"complete_data_type": "varchar(8000)",
			"conversion_type": null,
			"data_type": "varchar",
			"datetime_precision": null,
			"numeric_precision": 0,
			"numeric_scale": 0
		},
		{
			"character_maximum_length": 8000,
			"column_comment": "",
			"column_id": "datavault.s_component_s_dbt_stage_r_component_metric_u_dbt_stage_h.mindeccov",
			"column_is_used": true,
			"column_name": "mindeccov",
			"column_name_detail": "",
			"column_nq_id": "mindeccov",
			"column_order": 85,
			"column_type": "attribute",
			"complete_data_type": "varchar(8000)",
			"conversion_type": null,
			"data_type": "varchar",
			"datetime_precision": null,
			"numeric_precision": 0,
			"numeric_scale": 0
		},
		{
			"character_maximum_length": 8000,
			"column_comment": "",
			"column_id": "datavault.s_component_s_dbt_stage_r_component_metric_u_dbt_stage_h.testreportverdict",
			"column_is_used": true,
			"column_name": "testreportverdict",
			"column_name_detail": "",
			"column_nq_id": "testreportverdict",
			"column_order": 86,
			"column_type": "attribute",
			"complete_data_type": "varchar(8000)",
			"conversion_type": null,
			"data_type": "varchar",
			"datetime_precision": null,
			"numeric_precision": 0,
			"numeric_scale": 0
		},
		{
			"character_maximum_length": 8000,
			"column_comment": "",
			"column_id": "datavault.s_component_s_dbt_stage_r_component_metric_u_dbt_stage_h.status_runtimecoverage",
			"column_is_used": true,
			"column_name": "status_runtimecoverage",
			"column_name_detail": "",
			"column_nq_id": "status_runtimecoverage",
			"column_order": 87,
			"column_type": "attribute",
			"complete_data_type": "varchar(8000)",
			"conversion_type": null,
			"data_type": "varchar",
			"datetime_precision": null,
			"numeric_precision": 0,
			"numeric_scale": 0
		},
		{
			"character_maximum_length": 8000,
			"column_comment": "",
			"column_id": "datavault.s_component_s_dbt_stage_r_component_metric_u_dbt_stage_h.minfctcov",
			"column_is_used": true,
			"column_name": "minfctcov",
			"column_name_detail": "",
			"column_nq_id": "minfctcov",
			"column_order": 88,
			"column_type": "attribute",
			"complete_data_type": "varchar(8000)",
			"conversion_type": null,
			"data_type": "varchar",
			"datetime_precision": null,
			"numeric_precision": 0,
			"numeric_scale": 0
		},
		{
			"character_maximum_length": 8000,
			"column_comment": "",
			"column_id": "datavault.s_component_s_dbt_stage_r_component_metric_u_dbt_stage_h.deviations_maxopenperconfig",
			"column_is_used": true,
			"column_name": "deviations_maxopenperconfig",
			"column_name_detail": "",
			"column_nq_id": "deviations_maxopenperconfig",
			"column_order": 89,
			"column_type": "attribute",
			"complete_data_type": "varchar(8000)",
			"conversion_type": null,
			"data_type": "varchar",
			"datetime_precision": null,
			"numeric_precision": 0,
			"numeric_scale": 0
		},
		{
			"character_maximum_length": 8000,
			"column_comment": "",
			"column_id": "datavault.s_component_s_dbt_stage_r_component_metric_u_dbt_stage_h.misramessages",
			"column_is_used": true,
			"column_name": "misramessages",
			"column_name_detail": "",
			"column_nq_id": "misramessages",
			"column_order": 90,
			"column_type": "attribute",
			"complete_data_type": "varchar(8000)",
			"conversion_type": null,
			"data_type": "varchar",
			"datetime_precision": null,
			"numeric_precision": 0,
			"numeric_scale": 0
		},
		{
			"character_maximum_length": 8000,
			"column_comment": "",
			"column_id": "datavault.s_component_s_dbt_stage_r_component_metric_u_dbt_stage_h.nrofspecitemswhicharefulfilledwithdeviationandhavenodeviationtext",
			"column_is_used": true,
			"column_name": "nrofspecitemswhicharefulfilledwithdeviationandhavenodeviationtext",
			"column_name_detail": "",
			"column_nq_id": "nrofspecitemswhicharefulfilledwithdeviationandhavenodeviationtext",
			"column_order": 91,
			"column_type": "attribute",
			"complete_data_type": "varchar(8000)",
			"conversion_type": null,
			"data_type": "varchar",
			"datetime_precision": null,
			"numeric_precision": 0,
			"numeric_scale": 0
		},
		{
			"character_maximum_length": 8000,
			"column_comment": "",
			"column_id": "datavault.s_component_s_dbt_stage_r_component_metric_u_dbt_stage_h.vtrtcases",
			"column_is_used": true,
			"column_name": "vtrtcases",
			"column_name_detail": "",
			"column_nq_id": "vtrtcases",
			"column_order": 92,
			"column_type": "attribute",
			"complete_data_type": "varchar(8000)",
			"conversion_type": null,
			"data_type": "varchar",
			"datetime_precision": null,
			"numeric_precision": 0,
			"numeric_scale": 0
		},
		{
			"character_maximum_length": 8000,
			"column_comment": "",
			"column_id": "datavault.s_component_s_dbt_stage_r_component_metric_u_dbt_stage_h.openmajordeviations",
			"column_is_used": true,
			"column_name": "openmajordeviations",
			"column_name_detail": "",
			"column_nq_id": "openmajordeviations",
			"column_order": 93,
			"column_type": "attribute",
			"complete_data_type": "varchar(8000)",
			"conversion_type": null,
			"data_type": "varchar",
			"datetime_precision": null,
			"numeric_precision": 0,
			"numeric_scale": 0
		},
		{
			"character_maximum_length": 8000,
			"column_comment": "",
			"column_id": "datavault.s_component_s_dbt_stage_r_component_metric_u_dbt_stage_h.tcasestested",
			"column_is_used": true,
			"column_name": "tcasestested",
			"column_name_detail": "",
			"column_nq_id": "tcasestested",
			"column_order": 94,
			"column_type": "attribute",
			"complete_data_type": "varchar(8000)",
			"conversion_type": null,
			"data_type": "varchar",
			"datetime_precision": null,
			"numeric_precision": 0,
			"numeric_scale": 0
		},
		{
			"character_maximum_length": 8000,
			"column_comment": "",
			"column_id": "datavault.s_component_s_dbt_stage_r_component_metric_u_dbt_stage_h.creqs",
			"column_is_used": true,
			"column_name": "creqs",
			"column_name_detail": "",
			"column_nq_id": "creqs",
			"column_order": 95,
			"column_type": "attribute",
			"complete_data_type": "varchar(8000)",
			"conversion_type": null,
			"data_type": "varchar",
			"datetime_precision": null,
			"numeric_precision": 0,
			"numeric_scale": 0
		},
		{
			"character_maximum_length": 8000,
			"column_comment": "",
			"column_id": "datavault.s_component_s_dbt_stage_r_component_metric_u_dbt_stage_h.maxmif",
			"column_is_used": true,
			"column_name": "maxmif",
			"column_name_detail": "",
			"column_nq_id": "maxmif",
			"column_order": 96,
			"column_type": "attribute",
			"complete_data_type": "varchar(8000)",
			"conversion_type": null,
			"data_type": "varchar",
			"datetime_precision": null,
			"numeric_precision": 0,
			"numeric_scale": 0
		},
		{
			"character_maximum_length": 8000,
			"column_comment": "",
			"column_id": "datavault.s_component_s_dbt_stage_r_component_metric_u_dbt_stage_h.designfeatures",
			"column_is_used": true,
			"column_name": "designfeatures",
			"column_name_detail": "",
			"column_nq_id": "designfeatures",
			"column_order": 97,
			"column_type": "attribute",
			"complete_data_type": "varchar(8000)",
			"conversion_type": null,
			"data_type": "varchar",
			"datetime_precision": null,
			"numeric_precision": 0,
			"numeric_scale": 0
		},
		{
			"character_maximum_length": 8000,
			"column_comment": "",
			"column_id": "datavault.s_component_s_dbt_stage_r_component_metric_u_dbt_stage_h.openrequireddeviations",
			"column_is_used": true,
			"column_name": "openrequireddeviations",
			"column_name_detail": "",
			"column_nq_id": "openrequireddeviations",
			"column_order": 98,
			"column_type": "attribute",
			"complete_data_type": "varchar(8000)",
			"conversion_type": null,
			"data_type": "varchar",
			"datetime_precision": null,
			"numeric_precision": 0,
			"numeric_scale": 0
		},
		{
			"character_maximum_length": 8000,
			"column_comment": "",
			"column_id": "datavault.s_component_s_dbt_stage_r_component_metric_u_dbt_stage_h.deviations_maxperconfig",
			"column_is_used": true,
			"column_name": "deviations_maxperconfig",
			"column_name_detail": "",
			"column_nq_id": "deviations_maxperconfig",
			"column_order": 99,
			"column_type": "attribute",
			"complete_data_type": "varchar(8000)",
			"conversion_type": null,
			"data_type": "varchar",
			"datetime_precision": null,
			"numeric_precision": 0,
			"numeric_scale": 0
		},
		{
			"character_maximum_length": 8000,
			"column_comment": "",
			"column_id": "datavault.s_component_s_dbt_stage_r_component_metric_u_dbt_stage_h.testspecchapters",
			"column_is_used": true,
			"column_name": "testspecchapters",
			"column_name_detail": "",
			"column_nq_id": "testspecchapters",
			"column_order": 100,
			"column_type": "attribute",
			"complete_data_type": "varchar(8000)",
			"conversion_type": null,
			"data_type": "varchar",
			"datetime_precision": null,
			"numeric_precision": 0,
			"numeric_scale": 0
		},
		{
			"character_maximum_length": 8000,
			"column_comment": "",
			"column_id": "datavault.s_component_s_dbt_stage_r_component_metric_u_dbt_stage_h.configurationbranchcoverage_measured",
			"column_is_used": true,
			"column_name": "configurationbranchcoverage_measured",
			"column_name_detail": "",
			"column_nq_id": "configurationbranchcoverage_measured",
			"column_order": 101,
			"column_type": "attribute",
			"complete_data_type": "varchar(8000)",
			"conversion_type": null,
			"data_type": "varchar",
			"datetime_precision": null,
			"numeric_precision": 0,
			"numeric_scale": 0
		},
		{
			"character_maximum_length": 8000,
			"column_comment": "",
			"column_id": "datavault.s_component_s_dbt_stage_r_component_metric_u_dbt_stage_h.status_testreport_testresult",
			"column_is_used": true,
			"column_name": "status_testreport_testresult",
			"column_name_detail": "",
			"column_nq_id": "status_testreport_testresult",
			"column_order": 102,
			"column_type": "attribute",
			"complete_data_type": "varchar(8000)",
			"conversion_type": null,
			"data_type": "varchar",
			"datetime_precision": null,
			"numeric_precision": 0,
			"numeric_scale": 0
		},
		{
			"character_maximum_length": 8000,
			"column_comment": "",
			"column_id": "datavault.s_component_s_dbt_stage_r_component_metric_u_dbt_stage_h.overalldecisioncoverage",
			"column_is_used": true,
			"column_name": "overalldecisioncoverage",
			"column_name_detail": "",
			"column_nq_id": "overalldecisioncoverage",
			"column_order": 103,
			"column_type": "attribute",
			"complete_data_type": "varchar(8000)",
			"conversion_type": null,
			"data_type": "varchar",
			"datetime_precision": null,
			"numeric_precision": 0,
			"numeric_scale": 0
		},
		{
			"character_maximum_length": 8000,
			"column_comment": "",
			"column_id": "datavault.s_component_s_dbt_stage_r_component_metric_u_dbt_stage_h.nrofspecitems_relevant_notfulfilled",
			"column_is_used": true,
			"column_name": "nrofspecitems_relevant_notfulfilled",
			"column_name_detail": "",
			"column_nq_id": "nrofspecitems_relevant_notfulfilled",
			"column_order": 104,
			"column_type": "attribute",
			"complete_data_type": "varchar(8000)",
			"conversion_type": null,
			"data_type": "varchar",
			"datetime_precision": null,
			"numeric_precision": 0,
			"numeric_scale": 0
		}
	],
	"functional_suffix_id": "",
	"functional_suffix_name": "Default of COMPONENT_METRIC_U_DBT_STAGE",
	"hub_id": "h_component",
	"satellite_comment": "",
	"satellite_id": "s_component_s_dbt_stage_r_component_metric_u_dbt_stage",
	"satellite_is_prototype": false,
	"satellite_subject_area_name": "QM",
	"staging_resource_id": "component_metric_u_dbt_stage",
	"staging_table_id": "staging.dbt_stage_r_component_metric_u_dbt_stage",
	"system_id": "dbt_stage"
}