{
	"column_ids": [
		{
			"character_maximum_length": 2000000,
			"column_comment": "",
			"column_id": "DATAVAULT.S_XMLCOMPONENT_S_XMLINTERFACE_R_VI_XML_COMPONENT_U_STAGING_H.UPDATED",
			"column_is_used": true,
			"column_name": "UPDATED",
			"column_name_detail": "",
			"column_nq_id": "UPDATED",
			"column_order": 1,
			"column_type": "attribute",
			"complete_data_type": "VARCHAR(2000000) UTF8",
			"conversion_type": null,
			"data_type": "VARCHAR UTF8",
			"datetime_precision": null,
			"numeric_precision": null,
			"numeric_scale": null
		},
		{
			"character_maximum_length": 2000000,
			"column_comment": "",
			"column_id": "DATAVAULT.S_XMLCOMPONENT_S_XMLINTERFACE_R_VI_XML_COMPONENT_U_STAGING_H.NAMESPACE_GUID",
			"column_is_used": true,
			"column_name": "NAMESPACE_GUID",
			"column_name_detail": "",
			"column_nq_id": "NAMESPACE_GUID",
			"column_order": 2,
			"column_type": "attribute",
			"complete_data_type": "VARCHAR(2000000) UTF8",
			"conversion_type": null,
			"data_type": "VARCHAR UTF8",
			"datetime_precision": null,
			"numeric_precision": null,
			"numeric_scale": null
		},
		{
			"character_maximum_length": 2000000,
			"column_comment": "",
			"column_id": "DATAVAULT.S_XMLCOMPONENT_S_XMLINTERFACE_R_VI_XML_COMPONENT_U_STAGING_H.NAMESPACE_NAME",
			"column_is_used": true,
			"column_name": "NAMESPACE_NAME",
			"column_name_detail": "",
			"column_nq_id": "NAMESPACE_NAME",
			"column_order": 3,
			"column_type": "attribute",
			"complete_data_type": "VARCHAR(2000000) UTF8",
			"conversion_type": null,
			"data_type": "VARCHAR UTF8",
			"datetime_precision": null,
			"numeric_precision": null,
			"numeric_scale": null
		},
		{
			"character_maximum_length": 2000000,
			"column_comment": "",
			"column_id": "DATAVAULT.S_XMLCOMPONENT_S_XMLINTERFACE_R_VI_XML_COMPONENT_U_STAGING_H.PACKAGE_GUID",
			"column_is_used": true,
			"column_name": "PACKAGE_GUID",
			"column_name_detail": "",
			"column_nq_id": "PACKAGE_GUID",
			"column_order": 4,
			"column_type": "attribute",
			"complete_data_type": "VARCHAR(2000000) UTF8",
			"conversion_type": null,
			"data_type": "VARCHAR UTF8",
			"datetime_precision": null,
			"numeric_precision": null,
			"numeric_scale": null
		},
		{
			"character_maximum_length": 2000000,
			"column_comment": "",
			"column_id": "DATAVAULT.S_XMLCOMPONENT_S_XMLINTERFACE_R_VI_XML_COMPONENT_U_STAGING_H.PACKAGE_NAME",
			"column_is_used": true,
			"column_name": "PACKAGE_NAME",
			"column_name_detail": "",
			"column_nq_id": "PACKAGE_NAME",
			"column_order": 5,
			"column_type": "attribute",
			"complete_data_type": "VARCHAR(2000000) UTF8",
			"conversion_type": null,
			"data_type": "VARCHAR UTF8",
			"datetime_precision": null,
			"numeric_precision": null,
			"numeric_scale": null
		},
		{
			"character_maximum_length": 2000000,
			"column_comment": "",
			"column_id": "DATAVAULT.S_XMLCOMPONENT_S_XMLINTERFACE_R_VI_XML_COMPONENT_U_STAGING_H.PACKAGE_AUTOSARCLUSTER",
			"column_is_used": true,
			"column_name": "PACKAGE_AUTOSARCLUSTER",
			"column_name_detail": "",
			"column_nq_id": "PACKAGE_AUTOSARCLUSTER",
			"column_order": 6,
			"column_type": "attribute",
			"complete_data_type": "VARCHAR(2000000) UTF8",
			"conversion_type": null,
			"data_type": "VARCHAR UTF8",
			"datetime_precision": null,
			"numeric_precision": null,
			"numeric_scale": null
		},
		{
			"character_maximum_length": 2000000,
			"column_comment": "",
			"column_id": "DATAVAULT.S_XMLCOMPONENT_S_XMLINTERFACE_R_VI_XML_COMPONENT_U_STAGING_H.PACKAGE_CURRENTQUALITYPROCESS",
			"column_is_used": true,
			"column_name": "PACKAGE_CURRENTQUALITYPROCESS",
			"column_name_detail": "",
			"column_nq_id": "PACKAGE_CURRENTQUALITYPROCESS",
			"column_order": 7,
			"column_type": "attribute",
			"complete_data_type": "VARCHAR(2000000) UTF8",
			"conversion_type": null,
			"data_type": "VARCHAR UTF8",
			"datetime_precision": null,
			"numeric_precision": null,
			"numeric_scale": null
		},
		{
			"character_maximum_length": 2000000,
			"column_comment": "",
			"column_id": "DATAVAULT.S_XMLCOMPONENT_S_XMLINTERFACE_R_VI_XML_COMPONENT_U_STAGING_H.PACKAGE_DESCRIPTION",
			"column_is_used": true,
			"column_name": "PACKAGE_DESCRIPTION",
			"column_name_detail": "",
			"column_nq_id": "PACKAGE_DESCRIPTION",
			"column_order": 8,
			"column_type": "attribute",
			"complete_data_type": "VARCHAR(2000000) UTF8",
			"conversion_type": null,
			"data_type": "VARCHAR UTF8",
			"datetime_precision": null,
			"numeric_precision": null,
			"numeric_scale": null
		},
		{
			"character_maximum_length": 2000000,
			"column_comment": "",
			"column_id": "DATAVAULT.S_XMLCOMPONENT_S_XMLINTERFACE_R_VI_XML_COMPONENT_U_STAGING_H.PACKAGE_HASSAFETYREQUIREMENTS",
			"column_is_used": true,
			"column_name": "PACKAGE_HASSAFETYREQUIREMENTS",
			"column_name_detail": "",
			"column_nq_id": "PACKAGE_HASSAFETYREQUIREMENTS",
			"column_order": 9,
			"column_type": "attribute",
			"complete_data_type": "VARCHAR(2000000) UTF8",
			"conversion_type": null,
			"data_type": "VARCHAR UTF8",
			"datetime_precision": null,
			"numeric_precision": null,
			"numeric_scale": null
		},
		{
			"character_maximum_length": 2000000,
			"column_comment": "",
			"column_id": "DATAVAULT.S_XMLCOMPONENT_S_XMLINTERFACE_R_VI_XML_COMPONENT_U_STAGING_H.PACKAGE_LAYER",
			"column_is_used": true,
			"column_name": "PACKAGE_LAYER",
			"column_name_detail": "",
			"column_nq_id": "PACKAGE_LAYER",
			"column_order": 10,
			"column_type": "attribute",
			"complete_data_type": "VARCHAR(2000000) UTF8",
			"conversion_type": null,
			"data_type": "VARCHAR UTF8",
			"datetime_precision": null,
			"numeric_precision": null,
			"numeric_scale": null
		},
		{
			"character_maximum_length": 2000000,
			"column_comment": "",
			"column_id": "DATAVAULT.S_XMLCOMPONENT_S_XMLINTERFACE_R_VI_XML_COMPONENT_U_STAGING_H.PACKAGE_REPORTCLASSIFICATION",
			"column_is_used": true,
			"column_name": "PACKAGE_REPORTCLASSIFICATION",
			"column_name_detail": "",
			"column_nq_id": "PACKAGE_REPORTCLASSIFICATION",
			"column_order": 11,
			"column_type": "attribute",
			"complete_data_type": "VARCHAR(2000000) UTF8",
			"conversion_type": null,
			"data_type": "VARCHAR UTF8",
			"datetime_precision": null,
			"numeric_precision": null,
			"numeric_scale": null
		},
		{
			"character_maximum_length": 2000000,
			"column_comment": "",
			"column_id": "DATAVAULT.S_XMLCOMPONENT_S_XMLINTERFACE_R_VI_XML_COMPONENT_U_STAGING_H.PACKAGE_REPORTINGQSTATUS",
			"column_is_used": true,
			"column_name": "PACKAGE_REPORTINGQSTATUS",
			"column_name_detail": "",
			"column_nq_id": "PACKAGE_REPORTINGQSTATUS",
			"column_order": 12,
			"column_type": "attribute",
			"complete_data_type": "VARCHAR(2000000) UTF8",
			"conversion_type": null,
			"data_type": "VARCHAR UTF8",
			"datetime_precision": null,
			"numeric_precision": null,
			"numeric_scale": null
		},
		{
			"character_maximum_length": 2000000,
			"column_comment": "",
			"column_id": "DATAVAULT.S_XMLCOMPONENT_S_XMLINTERFACE_R_VI_XML_COMPONENT_U_STAGING_H.PACKAGE_SHORTNAME",
			"column_is_used": true,
			"column_name": "PACKAGE_SHORTNAME",
			"column_name_detail": "",
			"column_nq_id": "PACKAGE_SHORTNAME",
			"column_order": 13,
			"column_type": "attribute",
			"complete_data_type": "VARCHAR(2000000) UTF8",
			"conversion_type": null,
			"data_type": "VARCHAR UTF8",
			"datetime_precision": null,
			"numeric_precision": null,
			"numeric_scale": null
		},
		{
			"character_maximum_length": 2000000,
			"column_comment": "",
			"column_id": "DATAVAULT.S_XMLCOMPONENT_S_XMLINTERFACE_R_VI_XML_COMPONENT_U_STAGING_H.PACKAGE_TARGETQUALITYPROCESS",
			"column_is_used": true,
			"column_name": "PACKAGE_TARGETQUALITYPROCESS",
			"column_name_detail": "",
			"column_nq_id": "PACKAGE_TARGETQUALITYPROCESS",
			"column_order": 14,
			"column_type": "attribute",
			"complete_data_type": "VARCHAR(2000000) UTF8",
			"conversion_type": null,
			"data_type": "VARCHAR UTF8",
			"datetime_precision": null,
			"numeric_precision": null,
			"numeric_scale": null
		},
		{
			"character_maximum_length": 2000000,
			"column_comment": "",
			"column_id": "DATAVAULT.S_XMLCOMPONENT_S_XMLINTERFACE_R_VI_XML_COMPONENT_U_STAGING_H.PACKAGE_TARGETQUALITYSTATUS",
			"column_is_used": true,
			"column_name": "PACKAGE_TARGETQUALITYSTATUS",
			"column_name_detail": "",
			"column_nq_id": "PACKAGE_TARGETQUALITYSTATUS",
			"column_order": 15,
			"column_type": "attribute",
			"complete_data_type": "VARCHAR(2000000) UTF8",
			"conversion_type": null,
			"data_type": "VARCHAR UTF8",
			"datetime_precision": null,
			"numeric_precision": null,
			"numeric_scale": null
		},
		{
			"character_maximum_length": 2000000,
			"column_comment": "",
			"column_id": "DATAVAULT.S_XMLCOMPONENT_S_XMLINTERFACE_R_VI_XML_COMPONENT_U_STAGING_H.PACKAGE_USEDINPRODUCT",
			"column_is_used": true,
			"column_name": "PACKAGE_USEDINPRODUCT",
			"column_name_detail": "",
			"column_nq_id": "PACKAGE_USEDINPRODUCT",
			"column_order": 16,
			"column_type": "attribute",
			"complete_data_type": "VARCHAR(2000000) UTF8",
			"conversion_type": null,
			"data_type": "VARCHAR UTF8",
			"datetime_precision": null,
			"numeric_precision": null,
			"numeric_scale": null
		},
		{
			"character_maximum_length": 2000000,
			"column_comment": "",
			"column_id": "DATAVAULT.S_XMLCOMPONENT_S_XMLINTERFACE_R_VI_XML_COMPONENT_U_STAGING_H.PACKAGE_USERGUIDRESPONSIBLE",
			"column_is_used": true,
			"column_name": "PACKAGE_USERGUIDRESPONSIBLE",
			"column_name_detail": "",
			"column_nq_id": "PACKAGE_USERGUIDRESPONSIBLE",
			"column_order": 17,
			"column_type": "attribute",
			"complete_data_type": "VARCHAR(2000000) UTF8",
			"conversion_type": null,
			"data_type": "VARCHAR UTF8",
			"datetime_precision": null,
			"numeric_precision": null,
			"numeric_scale": null
		},
		{
			"character_maximum_length": 2000000,
			"column_comment": "",
			"column_id": "DATAVAULT.S_XMLCOMPONENT_S_XMLINTERFACE_R_VI_XML_COMPONENT_U_STAGING_H.COMPONENT_GUID",
			"column_is_used": true,
			"column_name": "COMPONENT_GUID",
			"column_name_detail": "",
			"column_nq_id": "COMPONENT_GUID",
			"column_order": 18,
			"column_type": "attribute",
			"complete_data_type": "VARCHAR(2000000) UTF8",
			"conversion_type": null,
			"data_type": "VARCHAR UTF8",
			"datetime_precision": null,
			"numeric_precision": null,
			"numeric_scale": null
		},
		{
			"character_maximum_length": 2000000,
			"column_comment": "",
			"column_id": "DATAVAULT.S_XMLCOMPONENT_S_XMLINTERFACE_R_VI_XML_COMPONENT_U_STAGING_H.COMPONENT_VERSION",
			"column_is_used": true,
			"column_name": "COMPONENT_VERSION",
			"column_name_detail": "",
			"column_nq_id": "COMPONENT_VERSION",
			"column_order": 19,
			"column_type": "attribute",
			"complete_data_type": "VARCHAR(2000000) UTF8",
			"conversion_type": null,
			"data_type": "VARCHAR UTF8",
			"datetime_precision": null,
			"numeric_precision": null,
			"numeric_scale": null
		},
		{
			"character_maximum_length": 2000000,
			"column_comment": "",
			"column_id": "DATAVAULT.S_XMLCOMPONENT_S_XMLINTERFACE_R_VI_XML_COMPONENT_U_STAGING_H.COMPONENT_IMPLEMENTATIONVERSION",
			"column_is_used": true,
			"column_name": "COMPONENT_IMPLEMENTATIONVERSION",
			"column_name_detail": "",
			"column_nq_id": "COMPONENT_IMPLEMENTATIONVERSION",
			"column_order": 20,
			"column_type": "attribute",
			"complete_data_type": "VARCHAR(2000000) UTF8",
			"conversion_type": null,
			"data_type": "VARCHAR UTF8",
			"datetime_precision": null,
			"numeric_precision": null,
			"numeric_scale": null
		},
		{
			"character_maximum_length": 2000000,
			"column_comment": "",
			"column_id": "DATAVAULT.S_XMLCOMPONENT_S_XMLINTERFACE_R_VI_XML_COMPONENT_U_STAGING_H.COMPONENT_CREATIONDATEALM",
			"column_is_used": true,
			"column_name": "COMPONENT_CREATIONDATEALM",
			"column_name_detail": "",
			"column_nq_id": "COMPONENT_CREATIONDATEALM",
			"column_order": 21,
			"column_type": "attribute",
			"complete_data_type": "VARCHAR(2000000) UTF8",
			"conversion_type": null,
			"data_type": "VARCHAR UTF8",
			"datetime_precision": null,
			"numeric_precision": null,
			"numeric_scale": null
		},
		{
			"character_maximum_length": 2000000,
			"column_comment": "",
			"column_id": "DATAVAULT.S_XMLCOMPONENT_S_XMLINTERFACE_R_VI_XML_COMPONENT_U_STAGING_H.COMPONENT_MODTIMEALM",
			"column_is_used": true,
			"column_name": "COMPONENT_MODTIMEALM",
			"column_name_detail": "",
			"column_nq_id": "COMPONENT_MODTIMEALM",
			"column_order": 22,
			"column_type": "attribute",
			"complete_data_type": "VARCHAR(2000000) UTF8",
			"conversion_type": null,
			"data_type": "VARCHAR UTF8",
			"datetime_precision": null,
			"numeric_precision": null,
			"numeric_scale": null
		},
		{
			"character_maximum_length": 2000000,
			"column_comment": "",
			"column_id": "DATAVAULT.S_XMLCOMPONENT_S_XMLINTERFACE_R_VI_XML_COMPONENT_U_STAGING_H.COMPONENT_REVISIONALM",
			"column_is_used": true,
			"column_name": "COMPONENT_REVISIONALM",
			"column_name_detail": "",
			"column_nq_id": "COMPONENT_REVISIONALM",
			"column_order": 23,
			"column_type": "attribute",
			"complete_data_type": "VARCHAR(2000000) UTF8",
			"conversion_type": null,
			"data_type": "VARCHAR UTF8",
			"datetime_precision": null,
			"numeric_precision": null,
			"numeric_scale": null
		},
		{
			"character_maximum_length": 2000000,
			"column_comment": "",
			"column_id": "DATAVAULT.S_XMLCOMPONENT_S_XMLINTERFACE_R_VI_XML_COMPONENT_U_STAGING_H.COMPONENT_CREATIONDATESVN",
			"column_is_used": true,
			"column_name": "COMPONENT_CREATIONDATESVN",
			"column_name_detail": "",
			"column_nq_id": "COMPONENT_CREATIONDATESVN",
			"column_order": 24,
			"column_type": "attribute",
			"complete_data_type": "VARCHAR(2000000) UTF8",
			"conversion_type": null,
			"data_type": "VARCHAR UTF8",
			"datetime_precision": null,
			"numeric_precision": null,
			"numeric_scale": null
		},
		{
			"character_maximum_length": 2000000,
			"column_comment": "",
			"column_id": "DATAVAULT.S_XMLCOMPONENT_S_XMLINTERFACE_R_VI_XML_COMPONENT_U_STAGING_H.COMPONENT_REVISIONSVN",
			"column_is_used": true,
			"column_name": "COMPONENT_REVISIONSVN",
			"column_name_detail": "",
			"column_nq_id": "COMPONENT_REVISIONSVN",
			"column_order": 25,
			"column_type": "attribute",
			"complete_data_type": "VARCHAR(2000000) UTF8",
			"conversion_type": null,
			"data_type": "VARCHAR UTF8",
			"datetime_precision": null,
			"numeric_precision": null,
			"numeric_scale": null
		},
		{
			"character_maximum_length": 2000000,
			"column_comment": "",
			"column_id": "DATAVAULT.S_XMLCOMPONENT_S_XMLINTERFACE_R_VI_XML_COMPONENT_U_STAGING_H.COMPONENT_LASTMODDATE",
			"column_is_used": true,
			"column_name": "COMPONENT_LASTMODDATE",
			"column_name_detail": "",
			"column_nq_id": "COMPONENT_LASTMODDATE",
			"column_order": 26,
			"column_type": "attribute",
			"complete_data_type": "VARCHAR(2000000) UTF8",
			"conversion_type": null,
			"data_type": "VARCHAR UTF8",
			"datetime_precision": null,
			"numeric_precision": null,
			"numeric_scale": null
		},
		{
			"character_maximum_length": 2000000,
			"column_comment": "",
			"column_id": "DATAVAULT.S_XMLCOMPONENT_S_XMLINTERFACE_R_VI_XML_COMPONENT_U_STAGING_H.COMPONENT_SERVERURL",
			"column_is_used": true,
			"column_name": "COMPONENT_SERVERURL",
			"column_name_detail": "",
			"column_nq_id": "COMPONENT_SERVERURL",
			"column_order": 27,
			"column_type": "attribute",
			"complete_data_type": "VARCHAR(2000000) UTF8",
			"conversion_type": null,
			"data_type": "VARCHAR UTF8",
			"datetime_precision": null,
			"numeric_precision": null,
			"numeric_scale": null
		},
		{
			"character_maximum_length": 2000000,
			"column_comment": "",
			"column_id": "DATAVAULT.S_XMLCOMPONENT_S_XMLINTERFACE_R_VI_XML_COMPONENT_U_STAGING_H.COMPONENT_DESCRIPTION",
			"column_is_used": true,
			"column_name": "COMPONENT_DESCRIPTION",
			"column_name_detail": "",
			"column_nq_id": "COMPONENT_DESCRIPTION",
			"column_order": 28,
			"column_type": "attribute",
			"complete_data_type": "VARCHAR(2000000) UTF8",
			"conversion_type": null,
			"data_type": "VARCHAR UTF8",
			"datetime_precision": null,
			"numeric_precision": null,
			"numeric_scale": null
		},
		{
			"character_maximum_length": 2000000,
			"column_comment": "",
			"column_id": "DATAVAULT.S_XMLCOMPONENT_S_XMLINTERFACE_R_VI_XML_COMPONENT_U_STAGING_H.COMPONENT_PATHTESTREPORTS",
			"column_is_used": true,
			"column_name": "COMPONENT_PATHTESTREPORTS",
			"column_name_detail": "",
			"column_nq_id": "COMPONENT_PATHTESTREPORTS",
			"column_order": 29,
			"column_type": "attribute",
			"complete_data_type": "VARCHAR(2000000) UTF8",
			"conversion_type": null,
			"data_type": "VARCHAR UTF8",
			"datetime_precision": null,
			"numeric_precision": null,
			"numeric_scale": null
		},
		{
			"character_maximum_length": 2000000,
			"column_comment": "",
			"column_id": "DATAVAULT.S_XMLCOMPONENT_S_XMLINTERFACE_R_VI_XML_COMPONENT_U_STAGING_H.COMPONENT_QAAPPROVALNOTE",
			"column_is_used": true,
			"column_name": "COMPONENT_QAAPPROVALNOTE",
			"column_name_detail": "",
			"column_nq_id": "COMPONENT_QAAPPROVALNOTE",
			"column_order": 30,
			"column_type": "attribute",
			"complete_data_type": "VARCHAR(2000000) UTF8",
			"conversion_type": null,
			"data_type": "VARCHAR UTF8",
			"datetime_precision": null,
			"numeric_precision": null,
			"numeric_scale": null
		},
		{
			"character_maximum_length": 2000000,
			"column_comment": "",
			"column_id": "DATAVAULT.S_XMLCOMPONENT_S_XMLINTERFACE_R_VI_XML_COMPONENT_U_STAGING_H.COMPONENT_QACHECK",
			"column_is_used": true,
			"column_name": "COMPONENT_QACHECK",
			"column_name_detail": "",
			"column_nq_id": "COMPONENT_QACHECK",
			"column_order": 31,
			"column_type": "attribute",
			"complete_data_type": "VARCHAR(2000000) UTF8",
			"conversion_type": null,
			"data_type": "VARCHAR UTF8",
			"datetime_precision": null,
			"numeric_precision": null,
			"numeric_scale": null
		},
		{
			"character_maximum_length": 2000000,
			"column_comment": "",
			"column_id": "DATAVAULT.S_XMLCOMPONENT_S_XMLINTERFACE_R_VI_XML_COMPONENT_U_STAGING_H.COMPONENT_QLEVEL",
			"column_is_used": true,
			"column_name": "COMPONENT_QLEVEL",
			"column_name_detail": "",
			"column_nq_id": "COMPONENT_QLEVEL",
			"column_order": 32,
			"column_type": "attribute",
			"complete_data_type": "VARCHAR(2000000) UTF8",
			"conversion_type": null,
			"data_type": "VARCHAR UTF8",
			"datetime_precision": null,
			"numeric_precision": null,
			"numeric_scale": null
		},
		{
			"character_maximum_length": 2000000,
			"column_comment": "",
			"column_id": "DATAVAULT.S_XMLCOMPONENT_S_XMLINTERFACE_R_VI_XML_COMPONENT_U_STAGING_H.COMPONENT_RELEASESTATEMENT",
			"column_is_used": true,
			"column_name": "COMPONENT_RELEASESTATEMENT",
			"column_name_detail": "",
			"column_nq_id": "COMPONENT_RELEASESTATEMENT",
			"column_order": 33,
			"column_type": "attribute",
			"complete_data_type": "VARCHAR(2000000) UTF8",
			"conversion_type": null,
			"data_type": "VARCHAR UTF8",
			"datetime_precision": null,
			"numeric_precision": null,
			"numeric_scale": null
		},
		{
			"character_maximum_length": 2000000,
			"column_comment": "",
			"column_id": "DATAVAULT.S_XMLCOMPONENT_S_XMLINTERFACE_R_VI_XML_COMPONENT_U_STAGING_H.COMPONENT_REVISIONTESTREPORTS",
			"column_is_used": true,
			"column_name": "COMPONENT_REVISIONTESTREPORTS",
			"column_name_detail": "",
			"column_nq_id": "COMPONENT_REVISIONTESTREPORTS",
			"column_order": 34,
			"column_type": "attribute",
			"complete_data_type": "VARCHAR(2000000) UTF8",
			"conversion_type": null,
			"data_type": "VARCHAR UTF8",
			"datetime_precision": null,
			"numeric_precision": null,
			"numeric_scale": null
		}
	],
	"functional_suffix_id": "",
	"functional_suffix_name": "Default of VI_XML_COMPONENT_U_STAGING",
	"hub_id": "H_XMLCOMPONENT",
	"satellite_comment": "",
	"satellite_id": "S_XMLCOMPONENT_S_XMLINTERFACE_R_VI_XML_COMPONENT_U_STAGING",
	"satellite_is_prototype": false,
	"satellite_subject_area_name": "",
	"staging_resource_id": "VI_XML_COMPONENT_U_STAGING",
	"staging_table_id": "STAGING.XMLINTERFACE_R_VI_XML_COMPONENT_U_STAGING",
	"system_id": "XMLINTERFACE"
}