{
	"businessobject_comment": "",
	"businessobject_display_name": "Component > DBT_RULE > Default",
	"businessobject_dropdown_entry_string": "Component",
	"businessobject_elements": [
		{
			"columns": [
				{
					"column_comment": "Business Key for Hub Component",
					"column_id": "DATAVAULT.H_COMPONENT.COMPONENT_BK",
					"column_name": "Business Key for Hub Component",
					"column_name_detail": "COMPONENT_BK",
					"column_nq_id": "COMPONENT_BK",
					"column_order": 1,
					"column_orig_name": "Business Key for Hub Component",
					"conversion_type": null
				}
			],
			"path_id": "{\"businessobject_path\":{\"hubs\":[{\"hub_id\":\"H_COMPONENT\"}]}}"
		},
		{
			"columns": [
				{
					"column_comment": "",
					"column_id": "DATAVAULT.S_COMPONENT_S_DBT_RULE_R_COMPONENT_METRICS_U_DBT_RULE_F_TEST_COVERAGE_METRICS_C.CREQsWithTraceToTCASE",
					"column_name": "CREQ-TCASE Tracebility",
					"column_name_detail": "CREQsWithTraceToTCASE",
					"column_nq_id": "CREQsWithTraceToTCASE",
					"column_order": 2,
					"column_orig_name": "CREQ-TCASE Tracebility",
					"complete_data_type": "DECIMAL(18,0)",
					"conversion_type": null
				}
			],
			"path_id": "{\"businessobject_path\":{\"hubs\":[{\"hub_id\":\"H_COMPONENT\",\"satellites\":[{\"satellite_id\":\"S_COMPONENT_S_DBT_RULE_R_COMPONENT_METRICS_U_DBT_RULE_F_TEST_COVERAGE_METRICS\"}]}]}}"
		}
	],
	"businessobject_set_id": "businessobject_set_H_COMPONENT",
	"businessobject_structure": null,
	"businessobject_view_id": "BUSINESSOBJECTS.COMPONENT_S_DBT_RULE",
	"dependent_objects": [
		{
			"object_id": "H_COMPONENT",
			"object_type": "hub"
		},
		{
			"object_id": "S_COMPONENT_S_DBT_RULE_R_COMPONENT_METRICS_U_DBT_RULE_F_TEST_COVERAGE_METRICS",
			"object_type": "satellite"
		}
	],
	"granularity_satellite_id": "S_COMPONENT_S_DBT_RULE_R_COMPONENT_METRICS_U_DBT_RULE_F_TEST_COVERAGE_METRICS",
	"system_id": "DBT_RULE",
	"system_name": "DBT_RULE"
}